tunet/__init__.py
tunet/tunet.py
tunet/xEncode.py
tunet-2.0.2.dist-info/METADATA
tunet-2.0.2.dist-info/RECORD
tunet-2.0.2.dist-info/WHEEL
tunet-2.0.2.dist-info/top_level.txt
