Metadata-Version: 2.1
Name: tunet
Version: 2.0.2
Summary: Tsinghua University Network (tunet) login and logout tools
Home-page: https://github.com/Yibo-Li/pytunet
Author: Yibo Li
Author-email: gansuliyibo@126.com
License: MIT
Keywords: tunet login logout
Platform: UNKNOWN
Requires-Dist: requests
